MANIFEST.in
README.md
setup.py
lecli/__init__.py
lecli/_version.py
lecli/api_utils.py
lecli/cli.py
lecli/response_utils.py
lecli/api_key/__init__.py
lecli/api_key/api.py
lecli/api_key/commands.py
lecli/log/__init__.py
lecli/log/api.py
lecli/log/commands.py
lecli/logset/__init__.py
lecli/logset/api.py
lecli/logset/commands.py
lecli/query/__init__.py
lecli/query/api.py
lecli/query/commands.py
lecli/saved_query/__init__.py
lecli/saved_query/api.py
lecli/saved_query/commands.py
lecli/team/__init__.py
lecli/team/api.py
lecli/team/commands.py
lecli/usage/__init__.py
lecli/usage/api.py
lecli/usage/commands.py
lecli/user/__init__.py
lecli/user/api.py
lecli/user/commands.py
logentries_lecli.egg-info/PKG-INFO
logentries_lecli.egg-info/SOURCES.txt
logentries_lecli.egg-info/dependency_links.txt
logentries_lecli.egg-info/entry_points.txt
logentries_lecli.egg-info/not-zip-safe
logentries_lecli.egg-info/requires.txt
logentries_lecli.egg-info/top_level.txt