Metadata-Version: 1.0
Name: logentries-lecli
Version: 1.1.1
Summary: Logentries Command Line Interface
Home-page: https://github.com/logentries/lecli
Author: John Fitzpatrick, Safa Topal
Author-email: john.fitzpatrick@rapid7.com, safa.topal@rapid7.com
License: MIT
Platform: UNKNOWN
